decide/__init__.py
decide/cli.py
decide/conftest.py
decide/gui.py
decide/log.py
decide/utils.py
decide/data/__init__.py
decide/data/database.py
decide/data/modelfactory.py
decide/data/reader.py
decide/data/types.py
decide/data/utils.py
decide/data/tests/__init__.py
decide/data/tests/conftest.py
decide/data/tests/test_database.py
decide/data/tests/test_modelfactory.py
decide/data/tests/test_read.py
decide/model/__init__.py
decide/model/base.py
decide/model/calculations.py
decide/model/equalgain.py
decide/model/randomrate.py
decide/model/utils.py
decide/model/observers/__init__.py
decide/model/observers/exchanges_writer.py
decide/model/observers/externalities.py
decide/model/observers/issue_development.py
decide/model/observers/logger.py
decide/model/observers/observer.py
decide/model/observers/sqliteobserver.py
decide/model/observers/tests/test_issue_development.py
decide/model/test/__init__.py
decide/model/test/test_abstractExchangeActor.py
decide/model/test/test_actor.py
decide/model/test/test_actorIssue.py
decide/model/test/test_calculations.py
decide/model/test/test_exchange.py
decide/model/test/test_issue.py
decide/model/test/test_model.py
decide/model/test/test_randomizedequalgain.py
decide/qt/__init__.py
decide/qt/utils.py
decide/qt/inputwindow/__init__.py
decide/qt/inputwindow/gui.py
decide/qt/inputwindow/models.py
decide/qt/inputwindow/signals.py
decide/qt/inputwindow/widgets.py
decide/qt/inputwindow/tests/__init__.py
decide/qt/inputwindow/tests/test_comment.py
decide/qt/inputwindow/tests/test_load.py
decide/qt/mainwindow/__init__.py
decide/qt/mainwindow/errordialog.py
decide/qt/mainwindow/errorgrid.py
decide/qt/mainwindow/gui.py
decide/qt/mainwindow/helpers.py
decide/qt/mainwindow/settings.py
decide/qt/mainwindow/signals.py
decide/qt/mainwindow/widgets.py
decide/qt/mainwindow/tests/__init__.py
decide/qt/mainwindow/tests/test_settings.py
decide/results/__init__.py
decide/results/covariance.py
decide/results/descriptives.py
decide/results/externalities.py
decide_exchange_model-2025.3.1.dist-info/METADATA
decide_exchange_model-2025.3.1.dist-info/WHEEL
decide_exchange_model-2025.3.1.dist-info/entry_points.txt
decide_exchange_model-2025.3.1.dist-info/licenses/LICENSE
decide_exchange_model-2025.3.1.dist-info/RECORD
