Metadata-Version: 2.4
Name: decide-exchange-model
Version: 2025.3.1
Summary: Decide exchange model
Author-email: Jelmer Draaijer <info@jelmert.nl>
License-File: LICENSE
Classifier: Programming Language :: Python :: 3 :: Only
Classifier: Programming Language :: Python :: 3.13
Requires-Python: ==3.13.*
Requires-Dist: blinker==1.9.0
Requires-Dist: matplotlib==3.10.7
Requires-Dist: numpy==2.3.4
Requires-Dist: pandas==2.3.3
Requires-Dist: peewee==3.14.4
Requires-Dist: pyqt6==6.10.0
Requires-Dist: requests
Requires-Dist: structlog==25.5
Requires-Dist: typer==0.20
Requires-Dist: typesystem==0.2.5
